dictrule/__init__.py
dictrule/__version__.py
dictrule/context.py
dictrule/dr_property.py
dictrule/exceptions.py
dictrule/generator.py
dictrule/rule.py
dictrule-0.3.0.dist-info/LICENSE
dictrule-0.3.0.dist-info/METADATA
dictrule-0.3.0.dist-info/WHEEL
dictrule-0.3.0.dist-info/top_level.txt
dictrule-0.3.0.dist-info/RECORD
