Metadata-Version: 2.1
Name: dictrule
Version: 0.3.0
Summary: Python rules defined by a dict and a text generator from the rules
Home-page: https://github.com/elhoangvu/dictrule
Author: Zooxy Le
Author-email: elhoangvu@gmail.com
License: MIT License
Project-URL: Documentation, https://github.com/elhoangvu/dictrule
Project-URL: Source, https://github.com/elhoangvu/dictrule
Classifier: Development Status :: 5 - Production/Stable
Classifier: Intended Audience :: Developers
Classifier: License :: OSI Approved :: MIT License
Classifier: Operating System :: OS Independent
Classifier: Programming Language :: Python
Classifier: Programming Language :: Python :: 3
Classifier: Programming Language :: Python :: 3.7
Classifier: Programming Language :: Python :: 3.8
Classifier: Programming Language :: Python :: 3.9
Classifier: Programming Language :: Python :: 3.10
Classifier: Programming Language :: Python :: 3.11
Classifier: Programming Language :: Python :: 3.12
Classifier: Programming Language :: Python :: 3 :: Only
Classifier: Programming Language :: Python :: Implementation :: PyPy
Classifier: Topic :: Software Development :: Libraries :: Python Modules
Classifier: Topic :: Text Processing :: Markup
Requires-Python: >=3.7
License-File: LICENSE
